setup.py
easycrf/__init__.py
easycrf/evaluation_script.py
easycrf/feature_script.py
easycrf/utils.py
easycrf.egg-info/PKG-INFO
easycrf.egg-info/SOURCES.txt
easycrf.egg-info/dependency_links.txt
easycrf.egg-info/requires.txt
easycrf.egg-info/top_level.txt