Metadata-Version: 1.0
Name: easycrf
Version: 0.1.0
Summary: Make it easy to define features for crf models.
Home-page: https://github.com/bitbender/NLPTools
Author: Patrick Kuhn
Author-email: patrick.kuhn@student.hpi.de
License: Apache Software License
Platform: UNKNOWN
